app_helper/__init__.py
app_helper/asgi.py
app_helper/base_test.py
app_helper/default_settings.py
app_helper/main.py
app_helper/pytest_runner.py
app_helper/runner.py
app_helper/server.py
app_helper/urls.py
app_helper/utils.py
app_helper/locale/en/LC_MESSAGES/django.po
app_helper/test_data/__init__.py
app_helper/test_data/models.py
app_helper/test_data/templates/base.html
app_helper/test_data/templates/fullwidth.html
app_helper/test_data/templates/page.html
django_app_helper-3.3.5.dist-info/licenses/LICENSE
djangocms_helper/__init__.py
tests/__init__.py
tests/test_base_classes.py
tests/test_commands.py
tests/test_others.py
tests/test_utils/__init__.py
tests/test_utils/cms_helper.py
tests/test_utils/cms_helper_custom.py
tests/test_utils/cms_helper_extra.py
tests/test_utils/cms_helper_extra_runner.py
tests/test_utils/conftest.py
tests/test_utils/helper.py
tests/test_utils/helper_no_cms.py
tests/test_utils/runners.py
tests/test_utils/custom_user/__init__.py
tests/test_utils/custom_user/models.py
tests/test_utils/example1/__init__.py
tests/test_utils/example1/cms_app.py
tests/test_utils/example1/cms_apps.py
tests/test_utils/example1/cms_plugins.py
tests/test_utils/example1/models.py
tests/test_utils/example1/urls.py
tests/test_utils/example1/views.py
tests/test_utils/example1/tests/__init__.py
tests/test_utils/example1/tests/test_fake.py
tests/test_utils/example1/tests/test_pytest.py
tests/test_utils/example2/__init__.py
tests/test_utils/example2/models.py
django_app_helper-3.3.5.dist-info/METADATA
django_app_helper-3.3.5.dist-info/WHEEL
django_app_helper-3.3.5.dist-info/entry_points.txt
django_app_helper-3.3.5.dist-info/top_level.txt
django_app_helper-3.3.5.dist-info/RECORD
