Metadata-Version: 2.4
Name: django-app-helper
Version: 3.3.5
Summary: Helper for django applications development
Home-page: https://github.com/nephila/django-app-helper
Author: Iacopo Spalletti
Author-email: i.spalletti@nephila.digital
License: GPLv2+
Project-URL: Documentation, https://django-app-helper.readthedocs.io/
Classifier: License :: OSI Approved :: GNU General Public License v2 or later (GPLv2+)
Classifier: Development Status :: 5 - Production/Stable
Classifier: Framework :: Django
Classifier: Framework :: Django :: 3.2
Classifier: Framework :: Django :: 4.1
Classifier: Framework :: Django :: 4.2
Classifier: Framework :: Django :: 5.0
Classifier: Programming Language :: Python
Classifier: Programming Language :: Python :: 3
Classifier: Programming Language :: Python :: 3.8
Classifier: Programming Language :: Python :: 3.9
Classifier: Programming Language :: Python :: 3.10
Classifier: Programming Language :: Python :: 3.11
Classifier: Programming Language :: Python :: 3.12
Requires-Python: >=3.7
License-File: LICENSE
Requires-Dist: dj-database-url
Requires-Dist: docopt
Requires-Dist: six
Requires-Dist: setuptools; python_version >= "3.12"
Provides-Extra: cms
Requires-Dist: django-cms<3.12,>=3.7; extra == "cms"
Provides-Extra: async
Requires-Dist: channels; extra == "async"
Requires-Dist: daphne; extra == "async"
Provides-Extra: docs
Requires-Dist: sphinx-rtd-theme; extra == "docs"
Dynamic: license-file
